odoo/addons/stock_picking_carrier_from_rule/README.rst
odoo/addons/stock_picking_carrier_from_rule/__init__.py
odoo/addons/stock_picking_carrier_from_rule/__manifest__.py
odoo/addons/stock_picking_carrier_from_rule/i18n/es.po
odoo/addons/stock_picking_carrier_from_rule/i18n/it.po
odoo/addons/stock_picking_carrier_from_rule/i18n/stock_picking_carrier_from_rule.pot
odoo/addons/stock_picking_carrier_from_rule/models/__init__.py
odoo/addons/stock_picking_carrier_from_rule/models/stock_move.py
odoo/addons/stock_picking_carrier_from_rule/readme/CONTRIBUTORS.md
odoo/addons/stock_picking_carrier_from_rule/readme/CREDITS.md
odoo/addons/stock_picking_carrier_from_rule/readme/DESCRIPTION.md
odoo/addons/stock_picking_carrier_from_rule/readme/ROADMAP.md
odoo/addons/stock_picking_carrier_from_rule/static/description/icon.png
odoo/addons/stock_picking_carrier_from_rule/static/description/index.html
odoo/addons/stock_picking_carrier_from_rule/tests/__init__.py
odoo/addons/stock_picking_carrier_from_rule/tests/test_stock_picking_carrier_from_rule.py
odoo_addon_stock_picking_carrier_from_rule-18.0.1.0.0.4.dist-info/METADATA
odoo_addon_stock_picking_carrier_from_rule-18.0.1.0.0.4.dist-info/WHEEL
odoo_addon_stock_picking_carrier_from_rule-18.0.1.0.0.4.dist-info/top_level.txt
odoo_addon_stock_picking_carrier_from_rule-18.0.1.0.0.4.dist-info/RECORD
