Metadata-Version: 2.1
Name: odoo-addon-stock_picking_carrier_from_rule
Version: 18.0.1.0.0.4
Requires-Python: >=3.10
Requires-Dist: odoo==18.0.*
Summary: Set the carrier on picking if the stock rule used has a partner address set with a delivery method.
Home-page: https://github.com/OCA/delivery-carrier
License: AGPL-3
Author: Camptocamp, Odoo Community Association (OCA)
Author-email: support@odoo-community.org
Classifier: Programming Language :: Python
Classifier: Framework :: Odoo
Classifier: Framework :: Odoo :: 18.0
Classifier: License :: OSI Approved :: GNU Affero General Public License v3
